Metadata-Version: 1.0
Name: bino-gauss-distributions
Version: 0.1
Summary: Gaussian and Binomial distributions
Home-page: UNKNOWN
Author: Ronny Ramírez
Author-email: UNKNOWN
License: UNKNOWN
Platform: UNKNOWN
